{
  "schemaVersion": "2.0",
  "slug": "course-schedule",
  "number": 207,
  "title": "Course Schedule",
  "difficulty": "medium",
  "topics": [
    "graph",
    "dynamic-programming"
  ],
  "patterns": [
    "topological-sort",
    "bfs"
  ],
  "statement": "There are a total of `numCourses` courses you have to take, labeled from `0` to `numCourses - 1`. You are given an array `prerequisites` where `prerequisites[i] = [a_i, b_i]` indicates that you **must** take course `b_i` first if you want to take course `a_i`.\n\n- For example, the pair `[0, 1]` indicates that to take course `0` you have to first take course `1`.\n\nReturn `true` if you can finish all courses. Otherwise, return `false`.\n\n**Example 1:**\n\n```\nInput: numCourses = 2, prerequisites = [[1,0]]\nOutput: true\nExplanation: There are a total of 2 courses to take. To take course 1 you should have finished course 0. So it is possible.\n```\n\n**Example 2:**\n\n```\nInput: numCourses = 2, prerequisites = [[1,0],[0,1]]\nOutput: false\nExplanation: To take course 1 you should have finished course 0, and to take course 0 you should also have finished course 1. So it is impossible.\n```\n\n**Constraints:**\n\n- `1 <= numCourses <= 2000`\n- `0 <= prerequisites.length <= 5000`\n- `prerequisites[i].length == 2`\n- `0 <= a_i, b_i < numCourses`\n- All the pairs prerequisites[i] are **unique**.",
  "hasVisualization": true,
  "isPremium": false,
  "supportsCustomInput": false,
  "supportsCompare": false,
  "recommendedApproachId": "kahn-topo-sort",
  "inputConstraints": {
    "fields": [
      {
        "name": "numCourses",
        "type": "int",
        "label": "Number of courses"
      },
      {
        "name": "prerequisites",
        "type": "int[]",
        "label": "Prerequisite pairs [a,b]",
        "placeholder": "1,0;0,1",
        "min": 0,
        "max": 1999,
        "minLen": 0,
        "maxLen": 5000
      }
    ],
    "maxSteps": 2000
  }
}
